odoo9_addon_base_optional_quick_create-9.0.1.0.0.99.dev15-py2.7-nspkg.pth
odoo9_addon_base_optional_quick_create-9.0.1.0.0.99.dev15.dist-info/DESCRIPTION.rst
odoo9_addon_base_optional_quick_create-9.0.1.0.0.99.dev15.dist-info/METADATA
odoo9_addon_base_optional_quick_create-9.0.1.0.0.99.dev15.dist-info/RECORD
odoo9_addon_base_optional_quick_create-9.0.1.0.0.99.dev15.dist-info/WHEEL
odoo9_addon_base_optional_quick_create-9.0.1.0.0.99.dev15.dist-info/metadata.json
odoo9_addon_base_optional_quick_create-9.0.1.0.0.99.dev15.dist-info/namespace_packages.txt
odoo9_addon_base_optional_quick_create-9.0.1.0.0.99.dev15.dist-info/top_level.txt
odoo_addons/base_optional_quick_create/README.rst
odoo_addons/base_optional_quick_create/__init__.py
odoo_addons/base_optional_quick_create/__openerp__.py
odoo_addons/base_optional_quick_create/i18n/base_optional_quick_create.pot
odoo_addons/base_optional_quick_create/i18n/ca.po
odoo_addons/base_optional_quick_create/i18n/de.po
odoo_addons/base_optional_quick_create/i18n/es.po
odoo_addons/base_optional_quick_create/i18n/es_ES.po
odoo_addons/base_optional_quick_create/i18n/eu.po
odoo_addons/base_optional_quick_create/i18n/fi.po
odoo_addons/base_optional_quick_create/i18n/fr.po
odoo_addons/base_optional_quick_create/i18n/hr.po
odoo_addons/base_optional_quick_create/i18n/hr_HR.po
odoo_addons/base_optional_quick_create/i18n/it.po
odoo_addons/base_optional_quick_create/i18n/nl.po
odoo_addons/base_optional_quick_create/i18n/pt_BR.po
odoo_addons/base_optional_quick_create/i18n/sl.po
odoo_addons/base_optional_quick_create/i18n/tr.po
odoo_addons/base_optional_quick_create/i18n/tr_TR.po
odoo_addons/base_optional_quick_create/i18n/zh_CN.po
odoo_addons/base_optional_quick_create/models/__init__.py
odoo_addons/base_optional_quick_create/models/ir_model.py
odoo_addons/base_optional_quick_create/static/description/icon.png
odoo_addons/base_optional_quick_create/views/model_view.xml
